okam/security/Key.py
okam/security/Signer.py
okam/security/__init__.py
okam_security-0.1.1.dist-info/LICENSE
okam_security-0.1.1.dist-info/METADATA
okam_security-0.1.1.dist-info/WHEEL
okam_security-0.1.1.dist-info/top_level.txt
okam_security-0.1.1.dist-info/RECORD
