Metadata-Version: 2.1
Name: okam-security
Version: 0.1.1
Summary: A Python port of the Mako (PHP framework) security library.
Home-page: https://github.com/freost/okam-security
Author: Frederic G. Østby
Author-email: frederic.g.ostby@gmail.com
License: UNKNOWN
Project-URL: Bug Tracker, https://github.com/freost/okam-security/issues
Project-URL: Source Code, https://github.com/freost/okam-security
Platform: UNKNOWN
Classifier: License :: OSI Approved :: BSD License
Classifier: Operating System :: OS Independent
Classifier: Programming Language :: Python :: 3.5
Classifier: Programming Language :: Python :: 3.6
Classifier: Programming Language :: Python :: 3.7
Classifier: Programming Language :: Python :: 3.8
Requires-Python: >=3.5
